kcaptcha/__init__.py
kcaptcha/apis.py
kcaptcha/core/__init__.py
kcaptcha/core/click.py
kcaptcha/core/ocr.py
kcaptcha/core/slide.py
kcaptcha/geetest/__init__.py
kcaptcha/imgs/__init__.py
kcaptcha/models/__init__.py
kcaptcha/models/charset.json
kcaptcha/models/charset_old.json
kcaptcha/models/common.onnx
kcaptcha/models/common_det.onnx
kcaptcha/models/common_old.onnx
kcaptcha/tools/__init__.py
kcaptcha-1.0.3.dist-info/METADATA
kcaptcha-1.0.3.dist-info/WHEEL
kcaptcha-1.0.3.dist-info/top_level.txt
kcaptcha-1.0.3.dist-info/RECORD
