Metadata-Version: 2.1
Name: kcaptcha
Version: 1.0.3
Summary: kill captcha
Home-page: UNKNOWN
Author: xpc
License: UNKNOWN
Platform: UNKNOWN
Classifier: Programming Language :: Python :: 3
Classifier: License :: OSI Approved :: MIT License
Classifier: Operating System :: OS Independent
Requires-Python: <3.10
Requires-Dist: numpy
Requires-Dist: onnxruntime
Requires-Dist: Pillow
Requires-Dist: opencv-python
Requires-Dist: loguru
